fast_readability/__init__.py
fast_readability/readability.py
fast_readability/js/JSDOMParser.js
fast_readability/js/Readability.js
fast_readability-0.0.1.dist-info/licenses/LICENSE
fast_readability-0.0.1.dist-info/METADATA
fast_readability-0.0.1.dist-info/WHEEL
fast_readability-0.0.1.dist-info/top_level.txt
fast_readability-0.0.1.dist-info/RECORD
