Metadata-Version: 2.4
Name: fast-readability
Version: 0.0.1
Summary: A fast HTML content extractor based on Mozilla's Readability.js
Home-page: https://github.com/jiankaiwang/fast-readability
Author: Jiankai Wang
Author-email: darkqiank <darkqiank@gmail.com>
License: MPL-2.0
Project-URL: Homepage, https://github.com/darkqiank/fast-readability
Project-URL: Repository, https://github.com/darkqiank/fast-readability.git
Project-URL: Bug Tracker, https://github.com/darkqiank/fast-readability/issues
Project-URL: Documentation, https://github.com/darkqiank/fast-readability#readme
Keywords: readability,html,content-extraction,web-scraping,text-processing
Classifier: Development Status :: 3 - Alpha
Classifier: Intended Audience :: Developers
Classifier: License :: OSI Approved :: Mozilla Public License 2.0 (MPL 2.0)
Classifier: Operating System :: OS Independent
Classifier: Programming Language :: Python :: 3
Classifier: Programming Language :: Python :: 3.7
Classifier: Programming Language :: Python :: 3.8
Classifier: Programming Language :: Python :: 3.9
Classifier: Programming Language :: Python :: 3.10
Classifier: Programming Language :: Python :: 3.11
Classifier: Programming Language :: Python :: 3.12
Classifier: Topic :: Software Development :: Libraries :: Python Modules
Classifier: Topic :: Text Processing :: Markup :: HTML
Classifier: Topic :: Internet :: WWW/HTTP :: Browsers
Classifier: Topic :: Text Processing :: Filters
Requires-Python: >=3.7
License-File: LICENSE
Requires-Dist: quickjs>=1.19.4
Requires-Dist: beautifulsoup4>=4.9.0
Provides-Extra: dev
Requires-Dist: pytest>=6.0; extra == "dev"
Requires-Dist: black>=22.0; extra == "dev"
Requires-Dist: flake8>=4.0; extra == "dev"
Requires-Dist: mypy>=0.900; extra == "dev"
Requires-Dist: pre-commit>=2.0; extra == "dev"
Provides-Extra: test
Requires-Dist: pytest>=6.0; extra == "test"
Requires-Dist: pytest-cov>=3.0; extra == "test"
Dynamic: author
Dynamic: home-page
Dynamic: license-file
Dynamic: requires-python
